tap_getresponse/__init__.py
tap_getresponse/client.py
tap_getresponse/schemas/newsletter_activities.json
tap_getresponse/schemas/newsletter_details.json
tap_getresponse/streams.py
tap_getresponse/tap.py
tap_getresponse-0.0.2.dist-info/LICENSE
tap_getresponse-0.0.2.dist-info/METADATA
tap_getresponse-0.0.2.dist-info/WHEEL
tap_getresponse-0.0.2.dist-info/entry_points.txt
tap_getresponse-0.0.2.dist-info/RECORD
