Metadata-Version: 2.1
Name: tap-getresponse
Version: 0.0.2
Summary: `tap-getresponse` is a Singer tap for GetResponse, built with the Meltano Singer SDK.
License: Apache-2.0
Keywords: ELT,GetResponse
Author: Leo Grosjean
Author-email: leo.bigjin@gmail.com
Requires-Python: >=3.7.1,<3.12
Classifier: License :: OSI Approved :: Apache Software License
Classifier: Programming Language :: Python :: 3
Classifier: Programming Language :: Python :: 3.8
Classifier: Programming Language :: Python :: 3.9
Classifier: Programming Language :: Python :: 3.10
Classifier: Programming Language :: Python :: 3.11
Provides-Extra: s3
Requires-Dist: fs-s3fs (>=1.1.1,<2.0.0) ; extra == "s3"
Requires-Dist: requests (>=2.31.0,<3.0.0)
Requires-Dist: singer-sdk (>=0.31.1,<0.32.0)
